Workbook

Sheet README
B2: Vietnam: who contributes to the state budget, financial year 2025
B4: Reading the list years
B5: CafeF labels a list by its PUBLICATION year, not the year of the payments.
B6: The lists published in 2026 measure amounts actually remitted in financial year 2025.
B7: This workbook uses those 2026-published lists throughout. A list labelled 2025 would be FY2024.
B8: Cross-check: PetroVietnam is VND 90,991 bn in both the 2026 VNTAX 200 and the STATE 100.
B10: Sources
B11: VNTAX 200: https://cafef.vn/du-lieu/vntax200/2026/top-200-doanh-nghiep.chn
B12: STATE 100: https://cafef.vn/du-lieu/state100/doanh-nghiep.chn
B13: PRIVATE 100: https://cafef.vn/du-lieu/private100/2026/top-100-doanh-nghiep.chn
B14: National outturn: GSO / Ministry of Finance, FY2025 revenue = VND 2,650.1 trillion.
B15: Units
... B49: Analysis prepared 4 September 2026.

Sheet Firm level
A1: Rank | B1: Enterprise (VN) | C1: Trading name | D1: Code | E1: Ownership | F1: Sector | G1: Sector (source, VN) | H1: Budget payment (VND bn) | I1: Share of list | J1: Ownership basis / note | K1: VAT domestic | L1: VAT imports | M1: Corporate income tax | N1: Personal income tax | O1: Land & land rent
A2: 1 | B2: Tập đoàn Vingroup - Công ty Cổ phần | C2: Vingroup | D2: VIC | E2: Private | F2: Real estate & construction | G2: Bất động sản, Ô tô | H2: 148773 | I2: =H2/$H$202 -> 0.15038908 | J2: CafeF PRIVATE 100 (2026) | K2: 23183 | M2: 17043 | N2: 5057 | O2: 93813
A3: 2 | B3: Tập đoàn Công nghiệp - Năng lượng Quốc gia Việt Nam | C3: PetroVietnam | D3: PVN | E3: SOE | F3: Oil, gas & fuels | G3: Dầu khí | H3: 90991 | I3: =H3/$H$202 -> 0.091979411 | J3: CafeF STATE 100 (2026) | K3: 12585 | L3: 8648 | M3: 14599 | N3: 1865
A4: 3 | B4: Tập đoàn Công nghiệp - Viễn thông Quân đội (Viettel) | C4: Viettel | D4: VIETTEL | E4: SOE | F4: Technology & telecom | G4: Công nghệ - Viễn thông - Truyền thông | H4: 42290 | I4: =H4/$H$202 -> 0.042749385 | J4: CafeF STATE 100 (2026)
A5: 4 | B5: Tập đoàn Xăng dầu Việt Nam | C5: Petrolimex | D5: PLX | E5: SOE | F5: Oil, gas & fuels | G5: Xăng dầu - khí đốt | H5: 30575 | I5: =H5/$H$202 -> 0.030907128 | J5: CafeF STATE 100 (2026) | K5: 3055 | L5: 6397 | M5: 727 | N5: 320
A6: 5 | B6: Công ty TNHH Nhà máy Bia Heineken Việt Nam | C6: Heineken Vietnam | D6: HEINEKEN | E6: FDI | F6: Food, beverage & brewing | G6: Bia rượu | H6: 27000 | I6: =H6/$H$202 -> 0.027293294 | J6: Heineken NV, foreign-controlled JV
A7: 6 | B7: Công ty Ô tô Toyota Việt Nam | C7: Toyota Vietnam | D7: TOYOTAVN | E7: FDI | F7: Automotive | G7: Ô tô | H7: 26000 | I7: =H7/$H$202 -> 0.026282431 | J7: Toyota (JP)
A8: 7 | B8: Công ty Cổ phần Tập đoàn Sunshine | C8: Sunshine Group | D8: KSF | E8: Private | F8: Real estate & construction | G8: Bất động sản - Xây dựng | H8: 24045 | I8: =H8/$H$202 -> 0.024306194 | J8: CafeF PRIVATE 100 (2026)
A9: 8 | B9: Tập đoàn Công nghiệp Than - Khoáng sản Việt Nam | C9: Vinacomin | D9: VINACOMIN | E9: SOE | F9: Coal & mining | G9: Than, Khoáng sản | H9: 24031 | I9: =H9/$H$202 -> 0.024292042 | J9: CafeF STATE 100 (2026) | K9: 3746 | L9: 2281 | M9: 1732 | O9: 423
A10: 9 | B10: Công ty TNHH Lọc hóa dầu Nghi Sơn | C10: NSRP | D10: NSRP | E10: FDI | F10: Oil, gas & fuels | G10: Dầu khí | H10: 23000 | I10: =H10/$H$202 -> 0.023249843 | J10: Idemitsu + KPI 70.2%, PVN 25.1%
A11: 10 | B11: Tổng Công ty Thuốc lá Việt Nam - Công ty TNHH MTV | C11: Vinataba | D11: VINATABA | E11: SOE | F11: Tobacco | G11: Thuốc lá | H11: 22335 | I11: =H11/$H$202 -> 0.022577619 | J11: CafeF STATE 100 (2026) | K11: 3546 | M11: 418
A12: 11 | B12: Liên doanh Việt - Nga Vietsovpetro | C12: Vietsovpetro | D12: VIETSOVPETRO | E12: SOE | F12: Oil, gas & fuels | G12: Dầu khí | H12: 21450 | I12: =H12/$H$202 -> 0.021683006 | J12: PVN 51% / Zarubezhneft 49%, state-controlled JV
A13: 12 | B13: CTCP Tập đoàn Trường Hải | C13: Thaco Group | D13: THA | E13: Private | F13: Automotive | G13: Ô tô | H13: 21158 | I13: =H13/$H$202 -> 0.021387834 | J13: CafeF PRIVATE 100 (2026)
A14: 13 | B14: Tập đoàn Điện lực Việt Nam - Công ty TNHH MTV | C14: EVN | D14: EVN | E14: SOE | F14: Power & electrical | G14: Điện năng | H14: 20891 | I14: =H14/$H$202 -> 0.021117933 | J14: CafeF STATE 100 (2026) | K14: 8367 | M14: 1201 | N14: 1163
A15: 14 | B15: Tổng CTCP Bia - Rượu - Nước giải khát Sài Gòn | C15: Sabeco | D15: SAB | E15: FDI | F15: Food, beverage & brewing | G15: Bia rượu | H15: 14917 | I15: =H15/$H$202 -> 0.015079039 | J15: ThaiBev 53.6%; MOIT 36% | K15: 2118 | M15: 1057 | N15: 120
A16: 15 | B16: Công ty TNHH Phát Triển Khu đô thị Nam Thăng Long | C16: Ciputra Hanoi | D16: CIPUTRAHN | E16: FDI | F16: Real estate & construction | G16: Bất động sản - Xây dựng | H16: 13600 | I16: =H16/$H$202 -> 0.013747733 | J16: Ciputra (ID) led JV with UDIC
A17: 16 | B17: Công ty Cổ phần Đầu tư phát triển Thành phố Thông minh Bắc Hà Nội | C17: NH Smart City | D17: NHSC | E17: Private | F17: Real estate & construction | G17: Bất động sản - Xây dựng | H17: 13171 | I17: =H17/$H$202 -> 0.013314073 | J17: CafeF PRIVATE 100 (2026)
A18: 17 | B18: Công ty cổ phần Tập đoàn Hòa Phát | C18: Hòa Phát Group | D18: HPG | E18: Private | F18: Steel & building materials | G18: Thép | H18: 12954 | I18: =H18/$H$202 -> 0.013094716 | J18: CafeF PRIVATE 100 (2026) | K18: 903 | L18: 8766 | M18: 1995 | N18: 211
A19: 18 | B19: Ngân hàng Thương mại cổ phần Ngoại thương Việt Nam | C19: Vietcombank | D19: VCB | E19: SOE | F19: Banking | G19: Ngân hàng | H19: 12494 | I19: =H19/$H$202 -> 0.012629719 | J19: CafeF STATE 100 (2026) | K19: 835 | M19: 9242
A20: 19 | B20: Tập đoàn Thành Công (TC Group) | C20: Thành Công Group | D20: TCGROUP | E20: Private | F20: Automotive | G20: Ô tô, Bất động sản | H20: 12441 | I20: =H20/$H$202 -> 0.012576143 | J20: CafeF PRIVATE 100 (2026)
A21: 20 | B21: Công ty Honda Việt Nam | C21: Honda Vietnam | D21: HONDA | E21: FDI | F21: Automotive | G21: Ô tô | H21: 11880 | I21: =H21/$H$202 -> 0.012009049 | J21: Honda (JP)
A22: 21 | B22: Ngân hàng Thương mại cổ phần Đầu tư và Phát triển Việt Nam | C22: BIDV | D22: BID | E22: SOE | F22: Banking | G22: Ngân hàng | H22: 11374 | I22: =H22/$H$202 -> 0.011497553 | J22: CafeF STATE 100 (2026) | K22: 1430 | M22: 6768
A23: 22 | B23: Công ty TNHH Ford Việt Nam | C23: Ford Vietnam | D23: FORDVN | E23: FDI | F23: Automotive | G23: Ô tô | H23: 11300 | I23: =H23/$H$202 -> 0.011422749 | J23: Ford (US)
A24: 23 | B24: Công ty Cổ phần FPT | C24: FPT | D24: FPT | E24: Private | F24: Technology & telecom | G24: Công nghệ - Viễn thông - Truyền thông | H24: 11291 | I24: =H24/$H$202 -> 0.011413651 | J24: CafeF PRIVATE 100 (2026) | K24: 6437 | M24: 2238 | N24: 2182
A25: 24 | B25: Ngân hàng TMCP Kỹ Thương Việt Nam | C25: Techcombank | D25: TCB | E25: Private | F25: Banking | G25: Ngân hàng | H25: 10984 | I25: =H25/$H$202 -> 0.011103316 | J25: CafeF PRIVATE 100 (2026) | K25: 760 | M25: 7178
A26: 25 | B26: Ngân hàng Thương mại Cổ phần Công thương Việt Nam | C26: Vietinbank | D26: CTG | E26: SOE | F26: Banking | G26: Ngân hàng | H26: 10057 | I26: =H26/$H$202 -> 0.010166246 | J26: CafeF STATE 100 (2026) | K26: 998 | M26: 7541
A27: 26 | B27: Ngân hàng Thương mại cổ phần Quân đội | C27: MB | D27: MBB | E27: SOE | F27: Banking | G27: Ngân hàng | H27: 10004 | I27: =H27/$H$202 -> 0.010112671 | J27: CafeF STATE 100 (2026) | K27: 1105 | M27: 6518
A28: 27 | B28: Tổng Công ty Đầu tư và Kinh doanh vốn Nhà nước | C28: SCIC | D28: SCIC | E28: SOE | F28: Finance & investment | G28: Đầu tư | H28: 8404 | I28: =H28/$H$202 -> 0.0084952904 | J28: CafeF STATE 100 (2026) | M28: 384
A29: 28 | B29: Ngân hàng Nông nghiệp và Phát triển Nông thôn Việt Nam | C29: Agribank | D29: AGRIBANK | E29: SOE | F29: Banking | G29: Ngân hàng | H29: 7854 | I29: =H29/$H$202 -> 0.0079393159 | J29: CafeF STATE 100 (2026) | K29: 763 | M29: 5658
A30: 29 | B30: Ngân hàng Thương mại Cổ phần Việt Nam Thịnh Vượng | C30: VPBank | D30: VPB | E30: Private | F30: Banking | G30: Ngân hàng | H30: 6883 | I30: =H30/$H$202 -> 0.0069577682 | J30: CafeF PRIVATE 100 (2026) | K30: 879 | M30: 4128
A31: 30 | B31: Công ty Đầu tư Tài chính Nhà nước T.P Hồ Chí Minh | C31: HFIC | D31: HFIC | E31: SOE | F31: Finance & investment | G31: Đầu tư | H31: 6794 | I31: =H31/$H$202 -> 0.0068678014 | J31: CafeF STATE 100 (2026) | K31: 1441 | M31: 683 | N31: 500 | O31: 339
A32: 31 | B32: Tập đoàn Bưu chính Viễn thông Việt Nam | C32: VNPT | D32: VNPT | E32: SOE | F32: Technology & telecom | G32: Công nghệ - Viễn thông - Truyền thông | H32: 6078 | I32: =H32/$H$202 -> 0.0061440237 | J32: CafeF STATE 100 (2026)
A33: 32 | B33: Ngân hàng Thương Mại Cổ Phần Á Châu | C33: ACB | D33: ACB | E33: Private | F33: Banking | G33: Ngân hàng | H33: 5782 | I33: =H33/$H$202 -> 0.0058448083 | J33: CafeF PRIVATE 100 (2026) | K33: 452 | M33: 4335
A34: 33 | B34: Tổng Công ty Cổ phần Đầu tư Xây dựng và Thương mại Việt Nam | C34: CTX Holdings | D34: CTX | E34: Private | F34: Real estate & construction | G34: Bất động sản - Xây dựng | H34: 5127 | I34: =H34/$H$202 -> 0.0051826932 | J34: CafeF PRIVATE 100 (2026) | K34: 76 | M34: 3 | O34: 4970
A35: 34 | B35: Tổng công ty Cảng hàng không Việt Nam - CTCP | C35: ACV | D35: ACV | E35: SOE | F35: Aviation | G35: Hàng không | H35: 4656 | I35: =H35/$H$202 -> 0.0047065769 | J35: CafeF STATE 100 (2026) | K35: 211 | M35: 2582 | N35: 403 | O35: 149
A36: 35 | B36: Công ty Cổ phần Tập đoàn MaSan | C36: Masan Group | D36: MSN | E36: Private | F36: Food, beverage & brewing | G36: Thực phẩm, Bán lẻ, Tài chính | H36: 4636 | I36: =H36/$H$202 -> 0.0046863596 | J36: CafeF PRIVATE 100 (2026) | K36: 1854 | M36: 1274 | N36: 393
A37: 36 | B37: Ngân hàng Thương mại Cổ phần Sài Gòn Tài Lộc | C37: Sacombank | D37: STB | E37: Private | F37: Banking | G37: Ngân hàng | H37: 4304 | I37: =H37/$H$202 -> 0.0043507532 | J37: CafeF PRIVATE 100 (2026) | K37: 830 | M37: 2773
A38: 37 | B38: Tổng Công ty Khánh Việt | C38: Khatoco | D38: KHATOCO | E38: SOE | F38: Tobacco | G38: Thuốc lá | H38: 4292 | I38: =H38/$H$202 -> 0.0043386228 | J38: CafeF STATE 100 (2026) | K38: 537 | L38: 78 | M38: 58
A39: 38 | B39: Tổng CTCP Bia - Rượu - Nước giải khát Hà Nội | C39: Habeco | D39: BHN | E39: SOE | F39: Food, beverage & brewing | G39: Bia rượu | H39: 4158 | I39: =H39/$H$202 -> 0.0042031672 | J39: CafeF STATE 100 (2026) | K39: 613 | M39: 155
A40: 39 | B40: Công ty Cổ phần Sữa Việt Nam | C40: Vinamilk | D40: VNM | E40: Private | F40: Food, beverage & brewing | G40: Thực phẩm | H40: 3856 | I40: =H40/$H$202 -> 0.0038978867 | J40: CafeF PRIVATE 100 (2026) | K40: 1777 | M40: 1536 | N40: 311
A41: 40 | B41: Ngân hàng TMCP Phát triển T.P Hồ Chí Minh | C41: HDBank | D41: HDB | E41: Private | F41: Banking | G41: Ngân hàng | H41: 3744 | I41: =H41/$H$202 -> 0.0037846701 | J41: CafeF PRIVATE 100 (2026) | K41: 521 | M41: 2592
A42: 41 | B42: Tổng Công ty Công nghiệp Sài Gòn - TNHH Một thành viên | C42: CNS | D42: CNS | E42: SOE | F42: Tobacco | G42: Thuốc lá | H42: 3691 | I42: =H42/$H$202 -> 0.0037310943 | J42: CafeF STATE 100 (2026) | K42: 421 | L42: 77 | M42: 107 | N42: 19
A43: 42 | B43: Tổng Công ty Thương mại Xuất nhập khẩu Thanh Lễ - CTCP | C43: Thalexim | D43: TLP | E43: Private | F43: Oil, gas & fuels | G43: Xăng dầu - khí đốt | H43: 3468 | I43: =H43/$H$202 -> 0.003505672 | J43: CafeF PRIVATE 100 (2026) | K43: 158 | L43: 913 | M43: 18
A44: 43 | B44: Tập đoàn Công nghiệp Cao su Việt Nam | C44: Vietnam Rubber Group | D44: GVR | E44: SOE | F44: Chemicals, plastics & rubber | G44: Cao su, Bất động sản | H44: 3413 | I44: =H44/$H$202 -> 0.0034500745 | J44: CafeF STATE 100 (2026) | K44: 858 | M44: 1232 | N44: 162 | O44: 751
A45: 44 | B45: Công ty Cổ phần Tập đoàn BIM | C45: BIM Group | D45: BIMGROUP | E45: Private | F45: Power & electrical | G45: Bất động sản, Điện năng | H45: 3316 | I45: =H45/$H$202 -> 0.0033520208 | J45: CafeF PRIVATE 100 (2026) | K45: 983 | M45: 859 | N45: 135
A46: 45 | B46: Ngân hàng Thương mại cổ phần Lộc Phát Việt Nam | C46: LPBank | D46: LPB | E46: Private | F46: Banking | G46: Ngân hàng | H46: 3298 | I46: =H46/$H$202 -> 0.0033338253 | J46: CafeF PRIVATE 100 (2026) | K46: 55 | M46: 2600
A47: 46 | B47: Tổng Công ty Hàng không Việt Nam - CTCP | C47: Vietnam Airlines | D47: HVN | E47: SOE | F47: Aviation | G47: Hàng không | H47: 3291 | I47: =H47/$H$202 -> 0.0033267492 | J47: CafeF STATE 100 (2026) | K47: 969 | M47: 416 | N47: 874
A48: 47 | B48: Sở Giao dịch Chứng khoán Việt Nam | C48: Vietnam Exchange | D48: VNEX | E48: SOE | F48: Finance & investment | G48: Tài chính | H48: 3283 | I48: =H48/$H$202 -> 0.0033186623 | J48: CafeF STATE 100 (2026) | K48: 6 | M48: 659
A49: 48 | B49: Ngân hàng Thương mại cổ phần Sài Gòn - Hà Nội | C49: SHB | D49: SHB | E49: Private | F49: Banking | G49: Ngân hàng | H49: 3249 | I49: =H49/$H$202 -> 0.003284293 | J49: CafeF PRIVATE 100 (2026) | K49: 320 | M49: 2309
A50: 49 | B50: Tổng Công ty Cấp nước Sài Gòn | C50: Sawaco | D50: SAWACO | E50: SOE | F50: Water & utilities | G50: Cấp thoát nước | H50: 3179 | I50: =H50/$H$202 -> 0.0032135326 | J50: CafeF STATE 100 (2026) | K50: 232 | M50: 337
A51: 50 | B51: Công ty cổ phần Đầu tư Bất động sản Taseco | C51: Taseco Land | D51: TAL | E51: Private | F51: Real estate & construction | G51: Bất động sản - Xây dựng | H51: 3148 | I51: =H51/$H$202 -> 0.0031821959 | J51: CafeF PRIVATE 100 (2026) | K51: 198 | M51: 195 | O51: 2728
A52: 51 | B52: Công ty TNHH ô tô Mitsubishi Việt Nam | C52: Mitsubishi Motors | D52: MMVN | E52: FDI | F52: Automotive | G52: Ô tô | H52: 3000 | I52: =H52/$H$202 -> 0.0030325882 | J52: Mitsubishi Motors (JP)
A53: 52 | B53: Công ty TNHH Apple Việt Nam | C53: Apple Việt Nam | D53: APPLE | E53: FDI | F53: Retail & trade | G53: Phân phối - Bán lẻ | H53: 3000 | I53: =H53/$H$202 -> 0.0030325882 | J53: Apple Inc (US)
A54: 53 | B54: Công ty TNHH MTV - Tổng Công ty Tân Cảng Sài Gòn | C54: Saigon New Port/SNP | D54: SNP | E54: SOE | F54: Logistics & transport | G54: Vận tải - Logistics | H54: 3000 | I54: =H54/$H$202 -> 0.0030325882 | J54: CafeF STATE 100 (2026)
A55: 54 | B55: Công ty TNHH Bia Carlsberg Việt Nam | C55: Carlsberg Việt Nam | D55: CARLSBERG | E55: FDI | F55: Food, beverage & brewing | G55: Bia rượu | H55: 3000 | I55: =H55/$H$202 -> 0.0030325882 | J55: Carlsberg (DK)
A56: 55 | B56: Tổng Công ty Quản lý bay Việt Nam | C56: VATM | D56: VATM | E56: SOE | F56: Aviation | G56: Hàng không | H56: 2948 | I56: =H56/$H$202 -> 0.0029800233 | J56: CafeF STATE 100 (2026) | M56: 358
A57: 56 | B57: Công ty Cổ phần Tập đoàn GELEX | C57: Gelex | D57: GEX | E57: Private | F57: Power & electrical | G57: Bất động sản, Thiết bị điện | H57: 2892 | I57: =H57/$H$202 -> 0.002923415 | J57: CafeF PRIVATE 100 (2026) | K57: 1572 | M57: 943 | N57: 198
A58: 57 | B58: Công ty cổ phần Phát triển Bất động sản Phát Đạt | C58: Phát Đạt | D58: PDR | E58: Private | F58: Real estate & construction | G58: Bất động sản - Xây dựng | H58: 2890 | I58: =H58/$H$202 -> 0.0029213933 | J58: CafeF PRIVATE 100 (2026) | K58: 46 | M58: 103 | O58: 2711
A59: 58 | B59: Công ty cổ phần Chứng khoán VPS | C59: VPS Securities | D59: VCK | E59: Private | F59: Securities | G59: Chứng khoán | H59: 2848 | I59: =H59/$H$202 -> 0.0028789371 | J59: CafeF PRIVATE 100 (2026) | K59: 13 | M59: 648 | N59: 2187
A60: 59 | B60: CÔNG TY TNHH MTV XỔ SỐ KIẾN THIẾT LONG AN | C60: Long An Lottery | D60: XSLA | E60: SOE | F60: Lottery | G60: Xổ số | H60: 2797 | I60: =H60/$H$202 -> 0.0028273831 | J60: CafeF STATE 100 (2026)
A61: 60 | B61: CÔNG TY TNHH MTV XỔ SỐ KIẾN THIẾT BẠC LIÊU | C61: Bạc Liêu Lottery | D61: XSBL | E61: SOE | F61: Lottery | G61: Xổ số | H61: 2751 | I61: =H61/$H$202 -> 0.0027808834 | J61: CafeF STATE 100 (2026) | K61: 640 | M61: 207
A62: 61 | B62: CÔNG TY TNHH MTV XỔ SỐ KIẾN THIẾT BÌNH DƯƠNG | C62: Bình Dương Lottery | D62: XSBINHDUONG | E62: SOE | F62: Lottery | G62: Xổ số | H62: 2749 | I62: =H62/$H$202 -> 0.0027788616 | J62: CafeF STATE 100 (2026) | K62: 630 | M62: 212
A63: 62 | B63: Ngân hàng Thương mại cổ phần Tiên Phong | C63: TPBank | D63: TPB | E63: Private | F63: Banking | G63: Ngân hàng | H63: 2744 | I63: =H63/$H$202 -> 0.0027738073 | J63: CafeF PRIVATE 100 (2026) | K63: 400 | M63: 1552
A64: 63 | B64: Công ty TNHH MTV Xổ Số Kiến Thiết Bến Tre | C64: Bến Tre Lottery | D64: XSBENTRE | E64: SOE | F64: Lottery | G64: Xổ số | H64: 2738 | I64: =H64/$H$202 -> 0.0027677422 | J64: CafeF STATE 100 (2026) | K64: 643 | M64: 207
A65: 64 | B65: Ngân hàng Thương mại cổ phần Quốc tế Việt Nam | C65: VIB | D65: VIB | E65: Private | F65: Banking | G65: Ngân hàng | H65: 2731 | I65: =H65/$H$202 -> 0.0027606661 | J65: CafeF PRIVATE 100 (2026) | K65: 262 | M65: 1944
A66: 65 | B66: Công ty TNHH MTV Xổ số kiến thiết Cà Mau | C66: Cà Mau Lottery | D66: XSCM | E66: SOE | F66: Lottery | G66: Xổ số | H66: 2721 | I66: =H66/$H$202 -> 0.0027505575 | J66: CafeF STATE 100 (2026) | K66: 640 | M66: 175
A67: 66 | B67: Công ty TNHH Xổ số kiến thiết tỉnh Tây Ninh | C67: Tây Ninh Lottery | D67: XSTN | E67: SOE | F67: Lottery | G67: Xổ số | H67: 2718 | I67: =H67/$H$202 -> 0.0027475249 | J67: CafeF STATE 100 (2026) | K67: 643 | M67: 195 | N67: 243
A68: 67 | B68: CÔNG TY TNHH MTV XỔ SỐ KIẾN THIẾT TỈNH ĐỒNG THÁP | C68: Đồng Tháp Lottery | D68: XSDT | E68: SOE | F68: Lottery | G68: Xổ số | H68: 2682 | I68: =H68/$H$202 -> 0.0027111338 | J68: CafeF STATE 100 (2026) | K68: 646 | M68: 190
A69: 68 | B69: CÔNG TY TNHH MTV XỔ SỐ KIẾN THIẾT KIÊN GIANG | C69: Kiên Giang Lottery | D69: XSKG | E69: SOE | F69: Lottery | G69: Xổ số | H69: 2680 | I69: =H69/$H$202 -> 0.0027091121 | J69: CafeF STATE 100 (2026) | K69: 659 | M69: 179
A70: 69 | B70: Xổ số kiến thiết tỉnh Trà Vinh | C70: Trà Vinh Lottery | D70: XSTV | E70: SOE | F70: Lottery | G70: Xổ số | H70: 2648 | I70: =H70/$H$202 -> 0.0026767645 | J70: CafeF STATE 100 (2026) | K70: 658 | M70: 170
A71: 70 | B71: Công ty TNHH MTV Xổ số kiến thiết Bình Thuận | C71: Bình Thuận Lottery | D71: XSBINHTHUAN | E71: SOE | F71: Lottery | G71: Xổ số | H71: 2635 | I71: =H71/$H$202 -> 0.0026636233 | J71: CafeF STATE 100 (2026) | K71: 642 | M71: 168
A72: 71 | B72: Công ty TNHH MTV Xổ số kiến thiết Vĩnh Long | C72: Vĩnh Long Lottery | D72: XSVL | E72: SOE | F72: Lottery | G72: Xổ số | H72: 2615 | I72: =H72/$H$202 -> 0.002643406 | J72: CafeF STATE 100 (2026) | K72: 644 | M72: 210
A73: 72 | B73: Tổng Công ty Thương mại Sài Gòn - TNHH MTV | C73: Satra | D73: SATRA | E73: SOE | F73: Retail & trade | G73: Phân phối - Bán lẻ | H73: 2602 | I73: =H73/$H$202 -> 0.0026302648 | J73: CafeF STATE 100 (2026) | M73: 51
A74: 73 | B74: CÔNG TY TNHH MTV XỔ SỐ KIẾN THIẾT TỈNH BÀ RỊA - VŨNG TÀU | C74: BRVT Lottery | D74: XSBRVT | E74: SOE | F74: Lottery | G74: Xổ số | H74: 2591 | I74: =H74/$H$202 -> 0.0026191453 | J74: CafeF STATE 100 (2026) | K74: 641 | M74: 166
A75: 74 | B75: Công ty TNHH MTV Xổ số kiến thiết Lâm Đồng | C75: Lâm Đồng Lottery | D75: XSLD | E75: SOE | F75: Lottery | G75: Xổ số | H75: 2579 | I75: =H75/$H$202 -> 0.002607015 | J75: CafeF STATE 100 (2026) | K75: 654 | M75: 182 | N75: 249
A76: 75 | B76: CÔNG TY TNHH MTV XỔ SỐ KIẾN THIẾT AN GIANG | C76: An Giang Lottery | D76: XSAG | E76: SOE | F76: Lottery | G76: Xổ số | H76: 2543 | I76: =H76/$H$202 -> 0.0025706239 | J76: CafeF STATE 100 (2026) | K76: 642 | M76: 157 | N76: 240
A77: 76 | B77: CÔNG TY TNHH MTV XỔ SỐ KIẾN THIẾT TIỀN GIANG | C77: Tiền Giang Lottery | D77: XSTG | E77: SOE | F77: Lottery | G77: Xổ số | H77: 2529 | I77: =H77/$H$202 -> 0.0025564718 | J77: CafeF STATE 100 (2026) | K77: 650 | M77: 140 | N77: 244
A78: 77 | B78: CÔNG TY TNHH MTV XỔ SỐ KIẾN THIẾT VÀ DỊCH VỤ TỔNG HỢP ĐỒNG NAI | C78: Đồng Nai Lottery | D78: XSDONGNAI | E78: SOE | F78: Lottery | G78: Xổ số | H78: 2460 | I78: =H78/$H$202 -> 0.0024867223 | J78: CafeF STATE 100 (2026) | K78: 646 | M78: 198
A79: 78 | B79: CÔNG TY TNHH NHÀ NƯỚC MTV XỔ SỐ KIẾN THIẾT CẦN THƠ | C79: Cần Thơ Lottery | D79: XSCT | E79: SOE | F79: Lottery | G79: Xổ số | H79: 2452 | I79: =H79/$H$202 -> 0.0024786354 | J79: CafeF STATE 100 (2026) | K79: 646 | M79: 185
A80: 79 | B80: Tổng Công ty Đông Bắc - BQP | C80: Necorp | D80: NECORP | E80: SOE | F80: Coal & mining | G80: Than, Khoáng sản | H80: 2444 | I80: =H80/$H$202 -> 0.0024705485 | J80: CafeF STATE 100 (2026) | K80: 673 | M80: 205
A81: 80 | B81: Công ty Cổ phần Bất động sản JS | C81: JS REAL ESTATE | D81: JSRE | E81: Private | F81: Real estate & construction | G81: Bất động sản - Xây dựng | H81: 2400 | I81: =H81/$H$202 -> 0.0024260706 | J81: CafeF PRIVATE 100 (2026)
A82: 81 | B82: Công ty cổ phần Đầu tư Phát triển Du lịch Phú Quốc | C82: Corona Casino & Resort | D82: DLPQ | E82: Private | F82: Tourism & hospitality | G82: Du lịch | H82: 2333 | I82: =H82/$H$202 -> 0.0023583428 | J82: CafeF PRIVATE 100 (2026) | K82: 1359 | M82: 63 | N82: 305
A83: 82 | B83: Công ty TNHH MTV Xổ số kiến thiết Sóc Trăng | C83: Sóc Trăng Lottery | D83: XSST | E83: SOE | F83: Lottery | G83: Xổ số | H83: 2321 | I83: =H83/$H$202 -> 0.0023462124 | J83: CafeF STATE 100 (2026)
A84: 83 | B84: Tập đoàn Hoá chất Việt Nam | C84: Vinachem | D84: VINACHEM | E84: SOE | F84: Chemicals, plastics & rubber | G84: Hóa chất | H84: 2268 | I84: =H84/$H$202 -> 0.0022926367 | J84: CafeF STATE 100 (2026) | K84: 781 | M84: 692 | N84: 112
A85: 84 | B85: Công ty TNHH MTV Xổ số điện toán Việt Nam | C85: Vietlott | D85: VIETLOTT | E85: SOE | F85: Lottery | G85: Xổ số | H85: 2265 | I85: =H85/$H$202 -> 0.0022896041 | J85: CafeF STATE 100 (2026) | K85: 791 | M85: 84 | N85: 263
A86: 85 | B86: Công ty Cổ phần Tasco | C86: TASCO | D86: HUT | E86: Private | F86: Automotive | G86: Ô tô, Hạ tầng | H86: 2227 | I86: =H86/$H$202 -> 0.0022511913 | J86: CafeF PRIVATE 100 (2026) | K86: 773 | M86: 206 | N86: 111
A87: 86 | B87: Công ty Cổ phần Vàng bạc Đá quý Phú Nhuận | C87: PNJ | D87: PNJ | E87: Private | F87: Retail & trade | G87: Bán lẻ | H87: 2128 | I87: =H87/$H$202 -> 0.0021511159 | J87: CafeF PRIVATE 100 (2026) | K87: 981 | M87: 608 | N87: 361
A88: 87 | B88: Công ty TNHH MTV Xổ số kiến thiết Hậu Giang | C88: Hậu Giang Lottery | D88: XSHG | E88: SOE | F88: Lottery | G88: Xổ số | H88: 2115 | I88: =H88/$H$202 -> 0.0021379747 | J88: CafeF STATE 100 (2026) | K88: 598 | M88: 111
A89: 88 | B89: Công ty Cổ phần đầu tư Thế giới di động | C89: Mobile World Group | D89: MWG | E89: Private | F89: Retail & trade | G89: Bán lẻ | H89: 2056 | I89: =H89/$H$202 -> 0.0020783338 | J89: CafeF PRIVATE 100 (2026) | K89: 21521 | M89: 1546 | N89: 457
A90: 89 | B90: Tổng Công ty Đầu tư Phát triển nhà và Đô thị-Công ty TNHH | C90: HUD | D90: HUDX | E90: SOE | F90: Real estate & construction | G90: Bất động sản - Xây dựng | H90: 1951 | I90: =H90/$H$202 -> 0.0019721932 | J90: CafeF STATE 100 (2026) | M90: 157 | O90: 1296
A91: 90 | B91: Công ty Cổ phần Cơ điện lạnh | C91: REE | D91: REE | E91: Private | F91: Power & electrical | G91: Xây lắp, điện năng, bất động sản | H91: 1943 | I91: =H91/$H$202 -> 0.0019641063 | J91: CafeF PRIVATE 100 (2026) | K91: 1060 | M91: 323
A92: 91 | B92: Công ty TNHH MTV Xổ số kiến thiết và dịch vụ tổng hợp Bình Phước | C92: Bình Phước Lottery | D92: XSBP | E92: SOE | F92: Lottery | G92: Xổ số | H92: 1910 | I92: =H92/$H$202 -> 0.0019307478 | J92: CafeF STATE 100 (2026) | K92: 496 | M92: 117
A93: 92 | B93: Công ty Cổ phần Vincom Retail | C93: Vincom Retail | D93: VRE | E93: Private | F93: Real estate & construction | G93: Bất động sản - Xây dựng | H93: 1900 | I93: =H93/$H$202 -> 0.0019206392 | J93: CafeF PRIVATE 100 (2026) | K93: 625 | M93: 1089
A94: 93 | B94: Công ty Cổ phần Tập đoàn VNG | C94: VNG Group | D94: VNZ | E94: Private | F94: Technology & telecom | G94: Công nghệ - Viễn thông - Truyền thông | H94: 1867 | I94: =H94/$H$202 -> 0.0018872807 | J94: CafeF PRIVATE 100 (2026) | K94: 1005 | M94: 48 | N94: 336
A95: 94 | B95: Công ty TNHH MTV Thương mại Dầu khí Đồng Tháp | C95: Petimex | D95: PDT | E95: SOE | F95: Oil, gas & fuels | G95: Xăng dầu - khí đốt | H95: 1819 | I95: =H95/$H$202 -> 0.0018387593 | J95: CafeF STATE 100 (2026) | M95: 25
A96: 95 | B96: Tập đoàn Bảo Việt | C96: BaoViet Holdings | D96: BVH | E96: SOE | F96: Insurance | G96: Bảo hiểm | H96: 1817 | I96: =H96/$H$202 -> 0.0018367376 | J96: CafeF STATE 100 (2026) | K96: 475 | M96: 535 | N96: 755
A97: 96 | B97: Công ty Cổ phần Hàng không Vietjet | C97: Vietjetair | D97: VJC | E97: Private | F97: Aviation | G97: Hàng không | H97: 1809 | I97: =H97/$H$202 -> 0.0018286507 | J97: CafeF PRIVATE 100 (2026) | K97: 558 | M97: 172 | N97: 611
A98: 97 | B98: Công ty cổ phần Chứng khoán SSI | C98: SSI | D98: SSI | E98: Private | F98: Securities | G98: Chứng khoán | H98: 1807 | I98: =H98/$H$202 -> 0.001826629 | J98: CafeF PRIVATE 100 (2026) | M98: 580 | N98: 1004
A99: 98 | B99: Ngân hàng Thương mại cổ phần Đông Nam Á | C99: Seabank | D99: SSB | E99: Private | F99: Banking | G99: Ngân hàng | H99: 1755 | I99: =H99/$H$202 -> 0.0017740641 | J99: CafeF PRIVATE 100 (2026) | K99: 124 | M99: 1331 | N99: 211
A100: 99 | B100: Công ty TNHH Phát triển THT | C100: Starlake | D100: STARLAKE | E100: FDI | F100: Real estate & construction | G100: Bất động sản - Xây dựng | H100: 1600 | I100: =H100/$H$202 -> 0.0016173804 | J100: THT Development, Daewoo E&C (KR)
...

Sheet By ownership
A1: Budget remittance by ownership, VNTAX 200, financial year 2025
A3: Ownership | B3: Firms | C3: Budget payment (VND bn) | D3: Share of list | E3: Share of national revenue | F3: Average per firm
A4: State-owned (SOE) | B4: =COUNTIF('Firm level'!$E$2:$E$201,"SOE") -> 74 | C4: =SUMIF('Firm level'!$E$2:$E$201,"SOE",'Firm level'!$H$2:$H$201) -> 445558 | D4: =C4/$C$7 -> 0.45039798 | E4: =C4/$B$10 -> 0.16812875 | F4: =C4/B4 -> 6021.0541
A5: Domestic private | B5: =COUNTIF('Firm level'!$E$2:$E$201,"Private") -> 99 | C5: =SUMIF('Firm level'!$E$2:$E$201,"Private",'Firm level'!$H$2:$H$201) -> 390311 | D5: =C5/$C$7 -> 0.39455084 | E5: =C5/$B$10 -> 0.14728161 | F5: =C5/B5 -> 3942.5354
A6: Foreign-invested (FDI) | B6: =COUNTIF('Firm level'!$E$2:$E$201,"FDI") -> 27 | C6: =SUMIF('Firm level'!$E$2:$E$201,"FDI",'Firm level'!$H$2:$H$201) -> 153385 | D6: =C6/$C$7 -> 0.15505118 | E6: =C6/$B$10 -> 0.057878948 | F6: =C6/B6 -> 5680.9259
A7: TOTAL, VNTAX 200 | B7: =SUM(B4:B6) -> 200 | C7: =SUM(C4:C6) -> 989254 | D7: =C7/$C$7 -> 1 | E7: =C7/$B$10 -> 0.37328931 | F7: =C7/B7 -> 4946.27
A10: Memo: total state budget revenue, FY2025 (VND bn) | B10: 2650100 | C10: Hardcoded input. Source: GSO/MoF FY2025 outturn, VND 2,650.1 trillion.
A12: State-owned | B12: =C4 -> 445558 | C12: =B12/$C$7 -> 0.45039798
A13: Non-state (private + FDI) | B13: =C5+C6 -> 543696 | C13: =B13/$C$7 -> 0.54960202

Sheet By sector
A1: Budget remittance by sector and ownership, financial year 2025
A3: Sector | B3: Firms | C3: SOE | D3: Domestic private | E3: FDI | F3: Total (VND bn) | G3: Share of list | H3: SOE share of sector
A4: Real estate & construction | B4: =COUNTIF('Firm level'!$F$2:$F$201,$A4) -> 32 | C4: =SUMIFS('Firm level'!$H$2:$H$201,'Firm level'!$F$2:$F$201,$A4,'Firm level'!$E$2:$E$201,"SOE") -> 5228 | D4: =SUMIFS('Firm level'!$H$2:$H$201,'Firm level'!$F$2:$F$201,$A4,'Firm level'!$E$2:$E$201,"Private") -> 213029 | E4: =SUMIFS('Firm level'!$H$2:$H$201,'Firm level'!$F$2:$F$201,$A4,'Firm level'!$E$2:$E$201,"FDI") -> 16577 | F4: =SUM(C4:E4) -> 234834 | G4: =F4/$F$26 -> 0.23738494 | H4: =IF(F4=0,"",C4/F4) -> 0.022262534
A5: Oil, gas & fuels | B5: =COUNTIF('Firm level'!$F$2:$F$201,$A5) -> 7 | C5: =SUMIFS('Firm level'!$H$2:$H$201,'Firm level'!$F$2:$F$201,$A5,'Firm level'!$E$2:$E$201,"SOE") -> 145800 | D5: =SUMIFS('Firm level'!$H$2:$H$201,'Firm level'!$F$2:$F$201,$A5,'Firm level'!$E$2:$E$201,"Private") -> 3468 | E5: =SUMIFS('Firm level'!$H$2:$H$201,'Firm level'!$F$2:$F$201,$A5,'Firm level'!$E$2:$E$201,"FDI") -> 23000 | F5: =SUM(C5:E5) -> 172268 | G5: =F5/$F$26 -> 0.1741393 | H5: =IF(F5=0,"",C5/F5) -> 0.84635568
A6: Banking | B6: =COUNTIF('Firm level'!$F$2:$F$201,$A6) -> 23 | C6: =SUMIFS('Firm level'!$H$2:$H$201,'Firm level'!$F$2:$F$201,$A6,'Firm level'!$E$2:$E$201,"SOE") -> 51783 | D6: =SUMIFS('Firm level'!$H$2:$H$201,'Firm level'!$F$2:$F$201,$A6,'Firm level'!$E$2:$E$201,"Private") -> 52126 | E6: =SUMIFS('Firm level'!$H$2:$H$201,'Firm level'!$F$2:$F$201,$A6,'Firm level'!$E$2:$E$201,"FDI") -> 694 | F6: =SUM(C6:E6) -> 104603 | G6: =F6/$F$26 -> 0.10573927 | H6: =IF(F6=0,"",C6/F6) -> 0.49504316
A7: Automotive | B7: =COUNTIF('Firm level'!$F$2:$F$201,$A7) -> 13 | C7: =SUMIFS('Firm level'!$H$2:$H$201,'Firm level'!$F$2:$F$201,$A7,'Firm level'!$E$2:$E$201,"SOE") -> 468 | D7: =SUMIFS('Firm level'!$H$2:$H$201,'Firm level'!$F$2:$F$201,$A7,'Firm level'!$E$2:$E$201,"Private") -> 39684 | E7: =SUMIFS('Firm level'!$H$2:$H$201,'Firm level'!$F$2:$F$201,$A7,'Firm level'!$E$2:$E$201,"FDI") -> 53180 | F7: =SUM(C7:E7) -> 93332 | G7: =F7/$F$26 -> 0.09434584 | H7: =IF(F7=0,"",C7/F7) -> 0.0050143573
A8: Food, beverage & brewing | B8: =COUNTIF('Firm level'!$F$2:$F$201,$A8) -> 19 | C8: =SUMIFS('Firm level'!$H$2:$H$201,'Firm level'!$F$2:$F$201,$A8,'Firm level'!$E$2:$E$201,"SOE") -> 4693 | D8: =SUMIFS('Firm level'!$H$2:$H$201,'Firm level'!$F$2:$F$201,$A8,'Firm level'!$E$2:$E$201,"Private") -> 16105 | E8: =SUMIFS('Firm level'!$H$2:$H$201,'Firm level'!$F$2:$F$201,$A8,'Firm level'!$E$2:$E$201,"FDI") -> 45917 | F8: =SUM(C8:E8) -> 66715 | G8: =F8/$F$26 -> 0.067439707 | H8: =IF(F8=0,"",C8/F8) -> 0.070344001
A9: Technology & telecom | B9: =COUNTIF('Firm level'!$F$2:$F$201,$A9) -> 8 | C9: =SUMIFS('Firm level'!$H$2:$H$201,'Firm level'!$F$2:$F$201,$A9,'Firm level'!$E$2:$E$201,"SOE") -> 49868 | D9: =SUMIFS('Firm level'!$H$2:$H$201,'Firm level'!$F$2:$F$201,$A9,'Firm level'!$E$2:$E$201,"Private") -> 14363 | E9: =SUMIFS('Firm level'!$H$2:$H$201,'Firm level'!$F$2:$F$201,$A9,'Firm level'!$E$2:$E$201,"FDI") -> 1000 | F9: =SUM(C9:E9) -> 65231 | G9: =F9/$F$26 -> 0.065939587 | H9: =IF(F9=0,"",C9/F9) -> 0.76448314
A10: Lottery | B10: =COUNTIF('Firm level'!$F$2:$F$201,$A10) -> 21 | C10: =SUMIFS('Firm level'!$H$2:$H$201,'Firm level'!$F$2:$F$201,$A10,'Firm level'!$E$2:$E$201,"SOE") -> 53499 | D10: =SUMIFS('Firm level'!$H$2:$H$201,'Firm level'!$F$2:$F$201,$A10,'Firm level'!$E$2:$E$201,"Private") -> 0 | E10: =SUMIFS('Firm level'!$H$2:$H$201,'Firm level'!$F$2:$F$201,$A10,'Firm level'!$E$2:$E$201,"FDI") -> 0 | F10: =SUM(C10:E10) -> 53499 | G10: =F10/$F$26 -> 0.054080145 | H10: =IF(F10=0,"",C10/F10) -> 1
A11: Power & electrical | B11: =COUNTIF('Firm level'!$F$2:$F$201,$A11) -> 7 | C11: =SUMIFS('Firm level'!$H$2:$H$201,'Firm level'!$F$2:$F$201,$A11,'Firm level'!$E$2:$E$201,"SOE") -> 20891 | D11: =SUMIFS('Firm level'!$H$2:$H$201,'Firm level'!$F$2:$F$201,$A11,'Firm level'!$E$2:$E$201,"Private") -> 11459 | E11: =SUMIFS('Firm level'!$H$2:$H$201,'Firm level'!$F$2:$F$201,$A11,'Firm level'!$E$2:$E$201,"FDI") -> 0 | F11: =SUM(C11:E11) -> 32350 | G11: =F11/$F$26 -> 0.032701409 | H11: =IF(F11=0,"",C11/F11) -> 0.64578053
A12: Tobacco | B12: =COUNTIF('Firm level'!$F$2:$F$201,$A12) -> 4 | C12: =SUMIFS('Firm level'!$H$2:$H$201,'Firm level'!$F$2:$F$201,$A12,'Firm level'!$E$2:$E$201,"SOE") -> 31720 | D12: =SUMIFS('Firm level'!$H$2:$H$201,'Firm level'!$F$2:$F$201,$A12,'Firm level'!$E$2:$E$201,"Private") -> 0 | E12: =SUMIFS('Firm level'!$H$2:$H$201,'Firm level'!$F$2:$F$201,$A12,'Firm level'!$E$2:$E$201,"FDI") -> 0 | F12: =SUM(C12:E12) -> 31720 | G12: =F12/$F$26 -> 0.032064566 | H12: =IF(F12=0,"",C12/F12) -> 1
A13: Coal & mining | B13: =COUNTIF('Firm level'!$F$2:$F$201,$A13) -> 3 | C13: =SUMIFS('Firm level'!$H$2:$H$201,'Firm level'!$F$2:$F$201,$A13,'Firm level'!$E$2:$E$201,"SOE") -> 26475 | D13: =SUMIFS('Firm level'!$H$2:$H$201,'Firm level'!$F$2:$F$201,$A13,'Firm level'!$E$2:$E$201,"Private") -> 748 | E13: =SUMIFS('Firm level'!$H$2:$H$201,'Firm level'!$F$2:$F$201,$A13,'Firm level'!$E$2:$E$201,"FDI") -> 0 | F13: =SUM(C13:E13) -> 27223 | G13: =F13/$F$26 -> 0.027518716 | H13: =IF(F13=0,"",C13/F13) -> 0.97252323
A14: Finance & investment | B14: =COUNTIF('Firm level'!$F$2:$F$201,$A14) -> 5 | C14: =SUMIFS('Firm level'!$H$2:$H$201,'Firm level'!$F$2:$F$201,$A14,'Firm level'!$E$2:$E$201,"SOE") -> 19083 | D14: =SUMIFS('Firm level'!$H$2:$H$201,'Firm level'!$F$2:$F$201,$A14,'Firm level'!$E$2:$E$201,"Private") -> 496 | E14: =SUMIFS('Firm level'!$H$2:$H$201,'Firm level'!$F$2:$F$201,$A14,'Firm level'!$E$2:$E$201,"FDI") -> 0 | F14: =SUM(C14:E14) -> 19579 | G14: =F14/$F$26 -> 0.019791681 | H14: =IF(F14=0,"",C14/F14) -> 0.97466673
A15: Steel & building materials | B15: =COUNTIF('Firm level'!$F$2:$F$201,$A15) -> 9 | C15: =SUMIFS('Firm level'!$H$2:$H$201,'Firm level'!$F$2:$F$201,$A15,'Firm level'!$E$2:$E$201,"SOE") -> 2037 | D15: =SUMIFS('Firm level'!$H$2:$H$201,'Firm level'!$F$2:$F$201,$A15,'Firm level'!$E$2:$E$201,"Private") -> 16315 | E15: =SUMIFS('Firm level'!$H$2:$H$201,'Firm level'!$F$2:$F$201,$A15,'Firm level'!$E$2:$E$201,"FDI") -> 488 | F15: =SUM(C15:E15) -> 18840 | G15: =F15/$F$26 -> 0.019044654 | H15: =IF(F15=0,"",C15/F15) -> 0.10812102
... A25: Textiles | B25: =COUNTIF('Firm level'!$F$2:$F$201,$A25) -> 1 | C25: =SUMIFS('Firm level'!$H$2:$H$201,'Firm level'!$F$2:$F$201,$A25,'Firm level'!$E$2:$E$201,"SOE") -> 895 | D25: =SUMIFS('Firm level'!$H$2:$H$201,'Firm level'!$F$2:$F$201,$A25,'Firm level'!$E$2:$E$201,"Private") -> 0 | E25: =SUMIFS('Firm level'!$H$2:$H$201,'Firm level'!$F$2:$F$201,$A25,'Firm level'!$E$2:$E$201,"FDI") -> 0 | F25: =SUM(C25:E25) -> 895 | G25: =F25/$F$26 -> 0.00090472214 | H25: =IF(F25=0,"",C25/F25) -> 1
A26: TOTAL | B26: =SUM(B4:B25) -> 200 | C26: =SUM(C4:C25) -> 445558 | D26: =SUM(D4:D25) -> 390311 | E26: =SUM(E4:E25) -> 153385 | F26: =SUM(F4:F25) -> 989254 | G26: =F26/$F$26 -> 1 | H26: =C26/F26 -> 0.45039798

Sheet Top 25 firms
A1: Twenty-five largest contributors, financial year 2025
A3: Rank | B3: Enterprise | C3: Ownership | D3: Sector | E3: Budget payment (VND bn) | F3: Cumulative share of list
A4: 1 | B4: Vingroup | C4: Private | D4: Real estate & construction | E4: 148773 | F4: =SUM($E$4:E4)/SUM('Firm level'!$H$2:$H$201) -> 0.15038908
A5: 2 | B5: PetroVietnam | C5: SOE | D5: Oil, gas & fuels | E5: 90991 | F5: =SUM($E$4:E5)/SUM('Firm level'!$H$2:$H$201) -> 0.24236849
A6: 3 | B6: Viettel | C6: SOE | D6: Technology & telecom | E6: 42290 | F6: =SUM($E$4:E6)/SUM('Firm level'!$H$2:$H$201) -> 0.28511788
A7: 4 | B7: Petrolimex | C7: SOE | D7: Oil, gas & fuels | E7: 30575 | F7: =SUM($E$4:E7)/SUM('Firm level'!$H$2:$H$201) -> 0.316025
A8: 5 | B8: Heineken Vietnam | C8: FDI | D8: Food, beverage & brewing | E8: 27000 | F8: =SUM($E$4:E8)/SUM('Firm level'!$H$2:$H$201) -> 0.3433183
A9: 6 | B9: Toyota Vietnam | C9: FDI | D9: Automotive | E9: 26000 | F9: =SUM($E$4:E9)/SUM('Firm level'!$H$2:$H$201) -> 0.36960073
A10: 7 | B10: Sunshine Group | C10: Private | D10: Real estate & construction | E10: 24045 | F10: =SUM($E$4:E10)/SUM('Firm level'!$H$2:$H$201) -> 0.39390692
A11: 8 | B11: Vinacomin | C11: SOE | D11: Coal & mining | E11: 24031 | F11: =SUM($E$4:E11)/SUM('Firm level'!$H$2:$H$201) -> 0.41819897
A12: 9 | B12: NSRP | C12: FDI | D12: Oil, gas & fuels | E12: 23000 | F12: =SUM($E$4:E12)/SUM('Firm level'!$H$2:$H$201) -> 0.44144881
A13: 10 | B13: Vinataba | C13: SOE | D13: Tobacco | E13: 22335 | F13: =SUM($E$4:E13)/SUM('Firm level'!$H$2:$H$201) -> 0.46402643
A14: 11 | B14: Vietsovpetro | C14: SOE | D14: Oil, gas & fuels | E14: 21450 | F14: =SUM($E$4:E14)/SUM('Firm level'!$H$2:$H$201) -> 0.48570943
A15: 12 | B15: Thaco Group | C15: Private | D15: Automotive | E15: 21158 | F15: =SUM($E$4:E15)/SUM('Firm level'!$H$2:$H$201) -> 0.50709727
... A28: 25 | B28: Vietinbank | C28: SOE | D28: Banking | E28: 10057 | F28: =SUM($E$4:E28)/SUM('Firm level'!$H$2:$H$201) -> 0.67626919

Sheet Tax mix
A1: Composition of budget remittance by ownership
A2: Only firms whose component detail is published are included, so rows do not sum to the headline totals.
A4: Ownership | B4: VAT domestic | C4: VAT on imports | D4: Corporate income tax | E4: Personal income tax | F4: Land & land rent | G4: Disclosed total
A5: State-owned (SOE) | B5: 60412 | C5: 17575 | D5: 68850 | E5: 7586 | F5: 4357 | G5: =SUM(B5:F5) -> 158780
A6: Domestic private | B6: 81885 | C6: 12381 | D6: 73890 | E6: 17512 | F6: 107480 | G6: =SUM(B6:F6) -> 293148
A7: Foreign-invested (FDI) | B7: 3337 | C7: 0 | D7: 5045 | E7: 641 | F7: 0 | G7: =SUM(B7:F7) -> 9023
A8: TOTAL | B8: =SUM(B5:B7) -> 145634 | C8: =SUM(C5:C7) -> 29956 | D8: =SUM(D5:D7) -> 147785 | E8: =SUM(E5:E7) -> 25739 | F8: =SUM(F5:F7) -> 111837 | G8: =SUM(G5:G7) -> 460951

Sheet STATE 100 firms
A1: STATE 100 (published 2026, payments made in financial year 2025)
A2: "Counts in group total" is FALSE for the 31 subsidiaries CafeF nets out to avoid double counting.
A4: Rank | B4: Enterprise | C4: Trading name | D4: Code | E4: Sector | F4: Sector (source, VN) | G4: Corporate group | H4: Role | I4: Counts in group total | J4: Budget payment | K4: VAT domestic | L4: VAT imports | M4: Corporate income tax | N4: Personal income tax | O4: Land & land rent | P4: Disclosed detail
A5: 1 | B5: Tập đoàn Công nghiệp - Năng lượng Quốc gia Việt Nam | C5: PetroVietnam | D5: PVN | E5: Oil & gas | F5: Dầu khí | G5: PetroVietnam | H5: Parent | I5: =TRUE() -> TRUE | J5: 90991 | K5: 12585 | L5: 8648 | M5: 14599 | N5: 1865 | P5: =SUM(K5:O5) -> 37697
A6: 2 | B6: Tập đoàn Công nghiệp - Viễn thông Quân đội (Viettel) | C6: Viettel | D6: VIETTEL | E6: Technology & telecom | F6: Công nghệ - Viễn thông - Truyền thông | G6: Viettel | H6: Parent | I6: =TRUE() -> TRUE | J6: 42290 | P6: =SUM(K6:O6) -> 0
A7: 3 | B7: Tập đoàn Xăng dầu Việt Nam | C7: Petrolimex | D7: PLX | E7: Fuel distribution | F7: Xăng dầu - khí đốt | G7: Petrolimex | H7: Parent | I7: =TRUE() -> TRUE | J7: 30575 | K7: 3055 | L7: 6397 | M7: 727 | N7: 320 | P7: =SUM(K7:O7) -> 10499
A8: 4 | B8: Tập đoàn Công nghiệp Than - Khoáng sản Việt Nam | C8: Vinacomin | D8: VINACOMIN | E8: Coal & minerals | F8: Than, Khoáng sản | G8: Vinacomin | H8: Parent | I8: =TRUE() -> TRUE | J8: 24031 | K8: 3746 | L8: 2281 | M8: 1732 | O8: 423 | P8: =SUM(K8:O8) -> 8182
A9: 5 | B9: Tổng Công ty Thuốc lá Việt Nam - Công ty TNHH MTV | C9: Vinataba | D9: VINATABA | E9: Tobacco | F9: Thuốc lá | G9: — | H9: Standalone | I9: =TRUE() -> TRUE | J9: 22335 | K9: 3546 | M9: 418 | P9: =SUM(K9:O9) -> 3964
A10: 6 | B10: Tập đoàn Điện lực Việt Nam - Công ty TNHH MTV | C10: EVN | D10: EVN | E10: Power | F10: Điện năng | G10: EVN | H10: Parent | I10: =TRUE() -> TRUE | J10: 20891 | K10: 8367 | M10: 1201 | N10: 1163 | P10: =SUM(K10:O10) -> 10731
A11: 7 | B11: Công ty TNHH - Tổng Công ty Thăm dò Khai thác Dầu khí | C11: PVEP | D11: PVEP | E11: Oil & gas | F11: Dầu khí | G11: PetroVietnam | H11: Subsidiary | I11: =FALSE() -> FALSE | J11: 15105 | M11: 6685 | P11: =SUM(K11:O11) -> 6685
A12: 8 | B12: Công ty Cổ phần - Tổng Công ty Lọc Hóa dầu Việt Nam | C12: BSR | D12: BSR | E12: Oil & gas | F12: Dầu khí | G12: PetroVietnam | H12: Subsidiary | I12: =FALSE() -> FALSE | J12: 14531 | K12: 3499 | L12: 4673 | M12: 390 | P12: =SUM(K12:O12) -> 8562
A13: 9 | B13: Ngân hàng Thương mại cổ phần Ngoại thương Việt Nam | C13: Vietcombank | D13: VCB | E13: Banking | F13: Ngân hàng | G13: — | H13: Standalone | I13: =TRUE() -> TRUE | J13: 12494 | K13: 835 | M13: 9242 | P13: =SUM(K13:O13) -> 10077
A14: 10 | B14: Ngân hàng Thương mại cổ phần Đầu tư và Phát triển Việt Nam | C14: BIDV | D14: BID | E14: Banking | F14: Ngân hàng | G14: BIDV | H14: Parent | I14: =TRUE() -> TRUE | J14: 11374 | K14: 1430 | M14: 6768 | P14: =SUM(K14:O14) -> 8198
A15: 11 | B15: Tổng Công ty Dầu Việt Nam - CTCP | C15: PV Oil | D15: OIL | E15: Fuel distribution | F15: Xăng dầu - khí đốt | G15: PetroVietnam | H15: Subsidiary | I15: =FALSE() -> FALSE | J15: 11115 | K15: 1006 | L15: 1328 | M15: 124 | P15: =SUM(K15:O15) -> 2458
A16: 12 | B16: Tổng Công ty cổ phần Đầu tư Quốc tế Viettel | C16: Viettel Global | D16: VGI | E16: Technology & telecom | F16: Công nghệ - Viễn thông - Truyền thông | G16: Viettel | H16: Subsidiary | I16: =FALSE() -> FALSE | J16: 10657 | K16: 3781 | M16: 3191 | N16: 970 | P16: =SUM(K16:O16) -> 7942
A17: 13 | B17: Ngân hàng Thương mại Cổ phần Công thương Việt Nam | C17: Vietinbank | D17: CTG | E17: Banking | F17: Ngân hàng | G17: — | H17: Standalone | I17: =TRUE() -> TRUE | J17: 10057 | K17: 998 | M17: 7541 | P17: =SUM(K17:O17) -> 8539
A18: 14 | B18: Ngân hàng Thương mại cổ phần Quân đội | C18: MB | D18: MBB | E18: Banking | F18: Ngân hàng | G18: MB | H18: Parent | I18: =TRUE() -> TRUE | J18: 10004 | K18: 1105 | M18: 6518 | P18: =SUM(K18:O18) -> 7623
A19: 15 | B19: Tổng Công ty Đầu tư và Kinh doanh vốn Nhà nước | C19: SCIC | D19: SCIC | E19: Finance & investment | F19: Đầu tư | G19: — | H19: Standalone | I19: =TRUE() -> TRUE | J19: 8404 | M19: 384 | P19: =SUM(K19:O19) -> 384
A20: 16 | B20: Ngân hàng Nông nghiệp và Phát triển Nông thôn Việt Nam | C20: Agribank | D20: AGRIBANK | E20: Banking | F20: Ngân hàng | G20: — | H20: Standalone | I20: =TRUE() -> TRUE | J20: 7854 | K20: 763 | M20: 5658 | P20: =SUM(K20:O20) -> 6421
A21: 17 | B21: Tổng Công ty Khí Việt Nam-CTCP | C21: PV Gas | D21: GAS | E21: Oil & gas | F21: Dầu khí | G21: PetroVietnam | H21: Subsidiary | I21: =FALSE() -> FALSE | J21: 7278 | K21: 1934 | L21: 2141 | M21: 2403 | P21: =SUM(K21:O21) -> 6478
A22: 18 | B22: Công ty Đầu tư Tài chính Nhà nước T.P Hồ Chí Minh | C22: HFIC | D22: HFIC | E22: Finance & investment | F22: Đầu tư | G22: HFIC | H22: Parent | I22: =TRUE() -> TRUE | J22: 6794 | K22: 1441 | M22: 683 | N22: 500 | O22: 339 | P22: =SUM(K22:O22) -> 2963
A23: 19 | B23: Công ty TNHH MTV Xổ số kiến thiết Thành phố Hồ Chí Minh | C23: HCM City Lottery | D23: XSHCM | E23: Lottery | F23: Xổ số | G23: HFIC | H23: Subsidiary | I23: =FALSE() -> FALSE | J23: 6176 | K23: 1378 | M23: 498 | N23: 490 | P23: =SUM(K23:O23) -> 2366
A24: 20 | B24: Tập đoàn Bưu chính Viễn thông Việt Nam | C24: VNPT | D24: VNPT | E24: Technology & telecom | F24: Công nghệ - Viễn thông - Truyền thông | G24: — | H24: Standalone | I24: =TRUE() -> TRUE | J24: 6078 | P24: =SUM(K24:O24) -> 0
A25: 21 | B25: Tổng Công ty Phát điện 1 | C25: EVN Genco1 | D25: GENCO1 | E25: Power | F25: Điện năng | G25: EVN | H25: Subsidiary | I25: =FALSE() -> FALSE | J25: 5422 | K25: 3521 | M25: 237 | P25: =SUM(K25:O25) -> 3758
A26: 22 | B26: Tổng công ty Cảng hàng không Việt Nam - CTCP | C26: ACV | D26: ACV | E26: Aviation | F26: Hàng không | G26: — | H26: Standalone | I26: =TRUE() -> TRUE | J26: 4656 | K26: 211 | M26: 2582 | N26: 403 | O26: 149 | P26: =SUM(K26:O26) -> 3345
A27: 23 | B27: Tổng Công ty Khánh Việt | C27: Khatoco | D27: KHATOCO | E27: Tobacco | F27: Thuốc lá | G27: — | H27: Standalone | I27: =TRUE() -> TRUE | J27: 4292 | K27: 537 | L27: 78 | M27: 58 | P27: =SUM(K27:O27) -> 673
A28: 24 | B28: Tổng CTCP Bia - Rượu - Nước giải khát Hà Nội | C28: Habeco | D28: BHN | E28: Food & beverage | F28: Bia rượu | G28: — | H28: Standalone | I28: =TRUE() -> TRUE | J28: 4158 | K28: 613 | M28: 155 | P28: =SUM(K28:O28) -> 768
A29: 25 | B29: Công ty Cổ phần Viễn thông FPT | C29: FPT Telecom | D29: FOX | E29: Technology & telecom | F29: Công nghệ - Viễn thông - Truyền thông | G29: — | H29: Standalone | I29: =TRUE() -> TRUE | J29: 3945 | K29: 2580 | M29: 955 | N29: 296 | P29: =SUM(K29:O29) -> 3831
A30: 26 | B30: Tổng Công ty Công nghiệp Sài Gòn - TNHH Một thành viên | C30: CNS | D30: CNS | E30: Tobacco | F30: Thuốc lá | G30: — | H30: Standalone | I30: =TRUE() -> TRUE | J30: 3691 | K30: 421 | L30: 77 | M30: 107 | N30: 19 | P30: =SUM(K30:O30) -> 624
A31: 27 | B31: Tập đoàn Công nghiệp Cao su Việt Nam | C31: Vietnam Rubber Group | D31: GVR | E31: Chemicals & rubber | F31: Cao su, Bất động sản | G31: — | H31: Standalone | I31: =TRUE() -> TRUE | J31: 3413 | K31: 858 | M31: 1232 | N31: 162 | O31: 751 | P31: =SUM(K31:O31) -> 3003
A32: 28 | B32: Tổng Công ty Hàng không Việt Nam - CTCP | C32: Vietnam Airlines | D32: HVN | E32: Aviation | F32: Hàng không | G32: — | H32: Standalone | I32: =TRUE() -> TRUE | J32: 3291 | K32: 969 | M32: 416 | N32: 874 | P32: =SUM(K32:O32) -> 2259
A33: 29 | B33: Sở Giao dịch Chứng khoán Việt Nam | C33: Vietnam Exchange | D33: VNEX | E33: Finance & investment | F33: Tài chính | G33: Vietnam Exchange | H33: Parent | I33: =TRUE() -> TRUE | J33: 3283 | K33: 6 | M33: 659 | P33: =SUM(K33:O33) -> 665
A34: 30 | B34: Tổng Công ty Cấp nước Sài Gòn | C34: Sawaco | D34: SAWACO | E34: Water | F34: Cấp thoát nước | G34: — | H34: Standalone | I34: =TRUE() -> TRUE | J34: 3179 | K34: 232 | M34: 337 | P34: =SUM(K34:O34) -> 569
A35: 31 | B35: Công ty TNHH MTV - Tổng Công ty Tân Cảng Sài Gòn | C35: Saigon New Port/SNP | D35: SNP | E35: Transport & logistics | F35: Vận tải - Logistics | G35: — | H35: Standalone | I35: =TRUE() -> TRUE | J35: 3000 | P35: =SUM(K35:O35) -> 0
A36: 32 | B36: Tổng Công ty Quản lý bay Việt Nam | C36: VATM | D36: VATM | E36: Aviation | F36: Hàng không | G36: — | H36: Standalone | I36: =TRUE() -> TRUE | J36: 2948 | M36: 358 | P36: =SUM(K36:O36) -> 358
A37: 33 | B37: CÔNG TY TNHH MTV XỔ SỐ KIẾN THIẾT LONG AN | C37: Long An Lottery | D37: XSLA | E37: Lottery | F37: Xổ số | G37: — | H37: Standalone | I37: =TRUE() -> TRUE | J37: 2797 | P37: =SUM(K37:O37) -> 0
A38: 34 | B38: CÔNG TY TNHH MTV XỔ SỐ KIẾN THIẾT BẠC LIÊU | C38: Bạc Liêu Lottery | D38: XSBL | E38: Lottery | F38: Xổ số | G38: — | H38: Standalone | I38: =TRUE() -> TRUE | J38: 2751 | K38: 640 | M38: 207 | P38: =SUM(K38:O38) -> 847
A39: 35 | B39: CÔNG TY TNHH MTV XỔ SỐ KIẾN THIẾT BÌNH DƯƠNG | C39: Bình Dương Lottery | D39: XSBINHDUONG | E39: Lottery | F39: Xổ số | G39: — | H39: Standalone | I39: =TRUE() -> TRUE | J39: 2749 | K39: 630 | M39: 212 | P39: =SUM(K39:O39) -> 842
A40: 36 | B40: Công ty TNHH MTV Xổ Số Kiến Thiết Bến Tre | C40: Bến Tre Lottery | D40: XSBENTRE | E40: Lottery | F40: Xổ số | G40: — | H40: Standalone | I40: =TRUE() -> TRUE | J40: 2738 | K40: 643 | M40: 207 | P40: =SUM(K40:O40) -> 850
A41: 37 | B41: Công ty TNHH MTV Xổ số kiến thiết Cà Mau | C41: Cà Mau Lottery | D41: XSCM | E41: Lottery | F41: Xổ số | G41: — | H41: Standalone | I41: =TRUE() -> TRUE | J41: 2721 | K41: 640 | M41: 175 | P41: =SUM(K41:O41) -> 815
A42: 38 | B42: Công ty TNHH Xổ số kiến thiết tỉnh Tây Ninh | C42: Tây Ninh Lottery | D42: XSTN | E42: Lottery | F42: Xổ số | G42: — | H42: Standalone | I42: =TRUE() -> TRUE | J42: 2718 | K42: 643 | M42: 195 | N42: 243 | P42: =SUM(K42:O42) -> 1081
A43: 39 | B43: CÔNG TY TNHH MTV XỔ SỐ KIẾN THIẾT TỈNH ĐỒNG THÁP | C43: Đồng Tháp Lottery | D43: XSDT | E43: Lottery | F43: Xổ số | G43: — | H43: Standalone | I43: =TRUE() -> TRUE | J43: 2682 | K43: 646 | M43: 190 | P43: =SUM(K43:O43) -> 836
A44: 40 | B44: CÔNG TY TNHH MTV XỔ SỐ KIẾN THIẾT KIÊN GIANG | C44: Kiên Giang Lottery | D44: XSKG | E44: Lottery | F44: Xổ số | G44: — | H44: Standalone | I44: =TRUE() -> TRUE | J44: 2680 | K44: 659 | M44: 179 | P44: =SUM(K44:O44) -> 838
A45: 41 | B45: Xổ số kiến thiết tỉnh Trà Vinh | C45: Trà Vinh Lottery | D45: XSTV | E45: Lottery | F45: Xổ số | G45: — | H45: Standalone | I45: =TRUE() -> TRUE | J45: 2648 | K45: 658 | M45: 170 | P45: =SUM(K45:O45) -> 828
A46: 42 | B46: Công ty TNHH MTV Xổ số kiến thiết Bình Thuận | C46: Bình Thuận Lottery | D46: XSBINHTHUAN | E46: Lottery | F46: Xổ số | G46: — | H46: Standalone | I46: =TRUE() -> TRUE | J46: 2635 | K46: 642 | M46: 168 | P46: =SUM(K46:O46) -> 810
A47: 43 | B47: Công ty TNHH MTV Xổ số kiến thiết Vĩnh Long | C47: Vĩnh Long Lottery | D47: XSVL | E47: Lottery | F47: Xổ số | G47: — | H47: Standalone | I47: =TRUE() -> TRUE | J47: 2615 | K47: 644 | M47: 210 | P47: =SUM(K47:O47) -> 854
A48: 44 | B48: Tổng Công ty Thương mại Sài Gòn - TNHH MTV | C48: Satra | D48: SATRA | E48: Retail & trade | F48: Phân phối - Bán lẻ | G48: — | H48: Standalone | I48: =TRUE() -> TRUE | J48: 2602 | M48: 51 | P48: =SUM(K48:O48) -> 51
A49: 45 | B49: CÔNG TY TNHH MTV XỔ SỐ KIẾN THIẾT TỈNH BÀ RỊA - VŨNG TÀU | C49: BRVT Lottery | D49: XSBRVT | E49: Lottery | F49: Xổ số | G49: — | H49: Standalone | I49: =TRUE() -> TRUE | J49: 2591 | K49: 641 | M49: 166 | P49: =SUM(K49:O49) -> 807
A50: 46 | B50: Công ty TNHH MTV Xổ số kiến thiết Lâm Đồng | C50: Lâm Đồng Lottery | D50: XSLD | E50: Lottery | F50: Xổ số | G50: — | H50: Standalone | I50: =TRUE() -> TRUE | J50: 2579 | K50: 654 | M50: 182 | N50: 249 | P50: =SUM(K50:O50) -> 1085
A51: 47 | B51: CÔNG TY TNHH MTV XỔ SỐ KIẾN THIẾT AN GIANG | C51: An Giang Lottery | D51: XSAG | E51: Lottery | F51: Xổ số | G51: — | H51: Standalone | I51: =TRUE() -> TRUE | J51: 2543 | K51: 642 | M51: 157 | N51: 240 | P51: =SUM(K51:O51) -> 1039
A52: 48 | B52: CÔNG TY TNHH MTV XỔ SỐ KIẾN THIẾT TIỀN GIANG | C52: Tiền Giang Lottery | D52: XSTG | E52: Lottery | F52: Xổ số | G52: — | H52: Standalone | I52: =TRUE() -> TRUE | J52: 2529 | K52: 650 | M52: 140 | N52: 244 | P52: =SUM(K52:O52) -> 1034
A53: 49 | B53: CÔNG TY TNHH MTV XỔ SỐ KIẾN THIẾT VÀ DỊCH VỤ TỔNG HỢP ĐỒNG NAI | C53: Đồng Nai Lottery | D53: XSDONGNAI | E53: Lottery | F53: Xổ số | G53: — | H53: Standalone | I53: =TRUE() -> TRUE | J53: 2460 | K53: 646 | M53: 198 | P53: =SUM(K53:O53) -> 844
A54: 50 | B54: CÔNG TY TNHH NHÀ NƯỚC MTV XỔ SỐ KIẾN THIẾT CẦN THƠ | C54: Cần Thơ Lottery | D54: XSCT | E54: Lottery | F54: Xổ số | G54: — | H54: Standalone | I54: =TRUE() -> TRUE | J54: 2452 | K54: 646 | M54: 185 | P54: =SUM(K54:O54) -> 831
A55: 51 | B55: Tổng Công ty Đông Bắc - BQP | C55: Necorp | D55: NECORP | E55: Coal & minerals | F55: Than, Khoáng sản | G55: — | H55: Standalone | I55: =TRUE() -> TRUE | J55: 2444 | K55: 673 | M55: 205 | P55: =SUM(K55:O55) -> 878
A56: 52 | B56: Công ty TNHH MTV Xổ số kiến thiết Sóc Trăng | C56: Sóc Trăng Lottery | D56: XSST | E56: Lottery | F56: Xổ số | G56: — | H56: Standalone | I56: =TRUE() -> TRUE | J56: 2321 | P56: =SUM(K56:O56) -> 0
A57: 53 | B57: Tập đoàn Hoá chất Việt Nam | C57: Vinachem | D57: VINACHEM | E57: Chemicals & rubber | F57: Hóa chất | G57: Vinachem | H57: Parent | I57: =TRUE() -> TRUE | J57: 2268 | K57: 781 | M57: 692 | N57: 112 | P57: =SUM(K57:O57) -> 1585
A58: 54 | B58: Công ty TNHH MTV Xổ số điện toán Việt Nam | C58: Vietlott | D58: VIETLOTT | E58: Lottery | F58: Xổ số | G58: — | H58: Standalone | I58: =TRUE() -> TRUE | J58: 2265 | K58: 791 | M58: 84 | N58: 263 | P58: =SUM(K58:O58) -> 1138
A59: 55 | B59: Công ty TNHH MTV Xổ số kiến thiết Hậu Giang | C59: Hậu Giang Lottery | D59: XSHG | E59: Lottery | F59: Xổ số | G59: — | H59: Standalone | I59: =TRUE() -> TRUE | J59: 2115 | K59: 598 | M59: 111 | P59: =SUM(K59:O59) -> 709
A60: 56 | B60: Tổng Công ty Khoáng sản TKV - CTCP | C60: Vimico | D60: KSV | E60: Coal & minerals | F60: Than, Khoáng sản | G60: Vinacomin | H60: Subsidiary | I60: =FALSE() -> FALSE | J60: 1968 | K60: 606 | M60: 360 | P60: =SUM(K60:O60) -> 966
A61: 57 | B61: Tổng Công ty Đầu tư Phát triển nhà và Đô thị-Công ty TNHH | C61: HUD | D61: HUDX | E61: Real estate & construction | F61: Bất động sản - Xây dựng | G61: — | H61: Standalone | I61: =TRUE() -> TRUE | J61: 1951 | M61: 157 | O61: 1296 | P61: =SUM(K61:O61) -> 1453
A62: 58 | B62: Tổng Công ty Cổ phần Dịch vụ Kỹ thuật Dầu khí Việt Nam | C62: PTSC | D62: PVS | E62: Oil & gas | F62: Dầu khí | G62: PetroVietnam | H62: Subsidiary | I62: =FALSE() -> FALSE | J62: 1921 | K62: 319 | M62: 620 | N62: 400 | P62: =SUM(K62:O62) -> 1339
A63: 59 | B63: Công ty TNHH MTV Xổ số kiến thiết và dịch vụ tổng hợp Bình Phước | C63: Bình Phước Lottery | D63: XSBP | E63: Lottery | F63: Xổ số | G63: — | H63: Standalone | I63: =TRUE() -> TRUE | J63: 1910 | K63: 496 | M63: 117 | P63: =SUM(K63:O63) -> 613
A64: 60 | B64: Công ty TNHH MTV Thương mại Dầu khí Đồng Tháp | C64: Petimex | D64: PDT | E64: Fuel distribution | F64: Xăng dầu - khí đốt | G64: — | H64: Standalone | I64: =TRUE() -> TRUE | J64: 1819 | M64: 25 | P64: =SUM(K64:O64) -> 25
A65: 61 | B65: Tập đoàn Bảo Việt | C65: BaoViet Holdings | D65: BVH | E65: Insurance | F65: Bảo hiểm | G65: Bao Viet | H65: Parent | I65: =TRUE() -> TRUE | J65: 1817 | K65: 475 | M65: 535 | N65: 755 | P65: =SUM(K65:O65) -> 1765
A66: 62 | B66: Tổng công ty Phát điện 2 - Công ty cổ phần | C66: EVN Genco2 | D66: GE2 | E66: Power | F66: Điện năng | G66: EVN | H66: Subsidiary | I66: =FALSE() -> FALSE | J66: 1815 | K66: 380 | M66: 231 | P66: =SUM(K66:O66) -> 611
A67: 63 | B67: Tổng Công ty Viễn thông Mobifone | C67: Mobifone | D67: MOBIFONE | E67: Technology & telecom | F67: Công nghệ - Viễn thông - Truyền thông | G67: — | H67: Standalone | I67: =TRUE() -> TRUE | J67: 1500 | P67: =SUM(K67:O67) -> 0
A68: 64 | B68: Tổng Công ty Du lịch Sài Gòn - TNHH Một thành viên | C68: Saigontourist | D68: SAIGONTOURIST | E68: Tourism | F68: Du lịch | G68: — | H68: Standalone | I68: =TRUE() -> TRUE | J68: 1439 | K68: 281 | M68: 78 | N68: 31 | O68: 742 | P68: =SUM(K68:O68) -> 1132
A69: 65 | B69: Tổng Công ty Công nghiệp Thực phẩm Đồng Nai | C69: Dofico | D69: DOFICO | E69: Tobacco | F69: Thuốc lá | G69: — | H69: Standalone | I69: =TRUE() -> TRUE | J69: 1402 | K69: 200 | M69: 28 | P69: =SUM(K69:O69) -> 228
A70: 66 | B70: Tổng Công ty Điện lực Dầu khí Việt Nam - CTCP | C70: PV Power | D70: POW | E70: Power | F70: Điện năng | G70: PetroVietnam | H70: Subsidiary | I70: =FALSE() -> FALSE | J70: 1174 | K70: 377 | M70: 121 | P70: =SUM(K70:O70) -> 498
A71: 67 | B71: Tổng Công ty Phát điện 3 - Công ty cổ phần | C71: EVN Genco3 | D71: PGV | E71: Power | F71: Điện năng | G71: EVN | H71: Subsidiary | I71: =FALSE() -> FALSE | J71: 1118 | K71: 335 | M71: 2 | N71: 98 | P71: =SUM(K71:O71) -> 435
A72: 68 | B72: Tổng Công ty Công nghiệp Xi măng Việt Nam | C72: Vicem | D72: VICEM | E72: Steel & building materials | F72: Vật liệu xây dựng | G72: — | H72: Standalone | I72: =TRUE() -> TRUE | J72: 1110 | K72: 386 | M72: 54 | P72: =SUM(K72:O72) -> 440
A73: 69 | B73: Tổng Công ty Hàng hải Việt Nam - CTCP | C73: VIMC | D73: MVN | E73: Transport & logistics | F73: Vận tải - Logistics | G73: — | H73: Standalone | I73: =TRUE() -> TRUE | J73: 1107 | K73: 395 | M73: 387 | N73: 143 | P73: =SUM(K73:O73) -> 925
A74: 70 | B74: Tổng Công ty cổ phần Bưu chính Viettel | C74: Viettel Post | D74: VTP | E74: Transport & logistics | F74: Vận tải - Logistics | G74: Viettel | H74: Subsidiary | I74: =FALSE() -> FALSE | J74: 1044 | K74: 685 | M74: 104 | N74: 246 | P74: =SUM(K74:O74) -> 1035
A75: 71 | B75: Tổng Công ty Cổ phần Khoan và Dịch vụ Khoan Dầu khí | C75: PV Drilling | D75: PVD | E75: Oil & gas | F75: Dầu khí | G75: PetroVietnam | H75: Subsidiary | I75: =FALSE() -> FALSE | J75: 1033 | K75: 120 | M75: 201 | N75: 360 | P75: =SUM(K75:O75) -> 681
A76: 72 | B76: Tổng Công ty Cổ phần Công trình Viettel | C76: Viettel Construction | D76: CTR | E76: Real estate & construction | F76: Xây lắp | G76: Viettel | H76: Subsidiary | I76: =FALSE() -> FALSE | J76: 995 | K76: 537 | M76: 142 | N76: 225 | P76: =SUM(K76:O76) -> 904
A77: 73 | B77: Tổng Công ty Điện lực Miền Bắc | C77: EVN NPC | D77: EVNNPC | E77: Power | F77: Điện năng | G77: EVN | H77: Subsidiary | I77: =FALSE() -> FALSE | J77: 991 | K77: 449 | M77: 196 | P77: =SUM(K77:O77) -> 645
A78: 74 | B78: Công ty TNHH MTV Dầu khí Thành phố Hồ Chí Minh | C78: Saigon Petro | D78: SAIGONPETRO | E78: Fuel distribution | F78: Xăng dầu - khí đốt | G78: — | H78: Standalone | I78: =TRUE() -> TRUE | J78: 965 | P78: =SUM(K78:O78) -> 0
A79: 75 | B79: Tổng Công ty Bảo Việt Nhân thọ | C79: BaoViet Life | D79: BVLIFE | E79: Insurance | F79: Bảo hiểm | G79: Bao Viet | H79: Subsidiary | I79: =FALSE() -> FALSE | J79: 946 | M79: 410 | P79: =SUM(K79:O79) -> 410
A80: 76 | B80: Tổng Công ty Thép Việt Nam - CTCP | C80: VNSteel | D80: TVN | E80: Steel & building materials | F80: Thép | G80: — | H80: Standalone | I80: =TRUE() -> TRUE | J80: 927 | K80: 637 | M80: 68 | O80: 110 | P80: =SUM(K80:O80) -> 815
A81: 77 | B81: Tập đoàn Dệt may Việt Nam | C81: Vinatex | D81: VGT | E81: Textiles | F81: Dệt may | G81: — | H81: Standalone | I81: =TRUE() -> TRUE | J81: 895 | K81: 462 | M81: 139 | O81: 212 | P81: =SUM(K81:O81) -> 813
A82: 78 | B82: Tổng Công ty Cổ phần phát triển khu Công nghiệp | C82: Sonadezi | D82: SNZ | E82: Real estate & construction | F82: Bất động sản - Xây dựng | G82: — | H82: Standalone | I82: =TRUE() -> TRUE | J82: 876 | K82: 175 | M82: 436 | P82: =SUM(K82:O82) -> 611
A83: 79 | B83: Công ty TNHH Nhôm Lâm Đồng - Vinacomin | C83: LDA | D83: LDAV | E83: Coal & minerals | F83: Than, Khoáng sản | G83: Vinacomin | H83: Subsidiary | I83: =FALSE() -> FALSE | J83: 858 | P83: =SUM(K83:O83) -> 0
A84: 80 | B84: Công ty TNHH Một thành viên - Tập đoàn Đường sắt Quốc gia Việt Nam | C84: Vietnam Railways | D84: VNRAILWAYS | E84: Transport & logistics | F84: Vận tải - Logistics | G84: — | H84: Standalone | I84: =TRUE() -> TRUE | J84: 852 | K84: 403 | M84: 25 | P84: =SUM(K84:O84) -> 428
A85: 81 | B85: Công ty cổ phần Chứng khoán MB | C85: MBS | D85: MBS | E85: Securities | F85: Chứng khoán | G85: MB | H85: Subsidiary | I85: =FALSE() -> FALSE | J85: 834 | K85: 4 | M85: 219 | N85: 598 | P85: =SUM(K85:O85) -> 821
A86: 82 | B86: Tổng Công ty Hóa dầu Petrolimex-CTCP | C86: PLC | D86: PLC | E86: Chemicals & rubber | F86: Hóa chất | G86: Petrolimex | H86: Subsidiary | I86: =FALSE() -> FALSE | J86: 819 | K86: 176 | L86: 547 | M86: 24 | P86: =SUM(K86:O86) -> 747
A87: 83 | B87: TỔNG CÔNG TY BƯU ĐIỆN VIỆT NAM | C87: VNPost | D87: VNPOST | E87: Transport & logistics | F87: Vận tải - Logistics | G87: — | H87: Standalone | I87: =TRUE() -> TRUE | J87: 789 | K87: 434 | M87: 117 | P87: =SUM(K87:O87) -> 551
A88: 84 | B88: Tổng Công ty Điện lực miền Trung | C88: EVN CPC | D88: EVNCPC | E88: Power | F88: Điện năng | G88: EVN | H88: Subsidiary | I88: =FALSE() -> FALSE | J88: 776 | K88: 533 | M88: 51 | P88: =SUM(K88:O88) -> 584
A89: 85 | B89: Tập đoàn Đầu tư và Phát triển công nghiệp Becamex - CTCP | C89: Becamex IDC | D89: BCM | E89: Real estate & construction | F89: Bất động sản - Xây dựng | G89: — | H89: Standalone | I89: =TRUE() -> TRUE | J89: 773 | K89: 320 | M89: 342 | P89: =SUM(K89:O89) -> 662
A90: 86 | B90: CTCP - Tổng Công ty Phân bón Dầu khí Cà Mau | C90: Đạm Cà Mau | D90: DCM | E90: Chemicals & rubber | F90: Hóa chất | G90: PetroVietnam | H90: Subsidiary | I90: =FALSE() -> FALSE | J90: 746 | L90: 129 | M90: 223 | P90: =SUM(K90:O90) -> 352
A91: 87 | B91: Tổng Công ty Điện lực Miền Nam | C91: EVN SPC | D91: EVNSPC | E91: Power | F91: Điện năng | G91: EVN | H91: Subsidiary | I91: =FALSE() -> FALSE | J91: 713 | M91: 28 | P91: =SUM(K91:O91) -> 28
A92: 88 | B92: Tổng Công ty Sông Đà - Công ty cổ phần | C92: Sông Đà Corp | D92: SJG | E92: Real estate & construction | F92: Xây dựng | G92: — | H92: Standalone | I92: =TRUE() -> TRUE | J92: 624 | K92: 182 | M92: 119 | P92: =SUM(K92:O92) -> 301
A93: 89 | B93: Tổng Công ty lưu ký và bù trừ Chứng khoán Việt Nam | C93: VSDC | D93: VSDC | E93: Finance & investment | F93: Tài chính | G93: — | H93: Standalone | I93: =TRUE() -> TRUE | J93: 602 | M93: 122 | P93: =SUM(K93:O93) -> 122
A94: 90 | B94: Tổng công ty Công nghiệp mỏ Việt Bắc TKV - CTCP | C94: VVMI | D94: MVB | E94: Coal & minerals | F94: Than, Khoáng sản | G94: Vinacomin | H94: Subsidiary | I94: =FALSE() -> FALSE | J94: 592 | K94: 150 | M94: 82 | N94: 13 | P94: =SUM(K94:O94) -> 245
A95: 91 | B95: Tổng công ty Cổ phần Vận tải Dầu khí | C95: PV Trans | D95: PVT | E95: Transport & logistics | F95: Vận tải - Logistics | G95: PetroVietnam | H95: Subsidiary | I95: =FALSE() -> FALSE | J95: 565 | M95: 368 | P95: =SUM(K95:O95) -> 368
A96: 92 | B96: Tổng Công ty Phân bón và Hóa chất Dầu khí-CTCP | C96: Đạm Phú Mỹ | D96: DPM | E96: Chemicals & rubber | F96: Hóa chất | G96: PetroVietnam | H96: Subsidiary | I96: =FALSE() -> FALSE | J96: 553 | M96: 283 | N96: 116 | P96: =SUM(K96:O96) -> 399
A97: 93 | B97: Tổng Công ty Đầu tư và phát triển Nhà Hà Nội | C97: Handico | D97: HANDICO | E97: Real estate & construction | F97: Bất động sản - Xây dựng | G97: — | H97: Standalone | I97: =TRUE() -> TRUE | J97: 543 | M97: 11 | O97: 335 | P97: =SUM(K97:O97) -> 346
A98: 94 | B98: Công ty TNHH Nhà nước MTV Yến sào Khánh Hòa | C98: Yến Sào Khánh Hòa | D98: YSKH | E98: Food & beverage | F98: Thực phẩm | G98: — | H98: Standalone | I98: =TRUE() -> TRUE | J98: 535 | K98: 160 | M98: 100 | P98: =SUM(K98:O98) -> 260
A99: 95 | B99: Sở Giao dịch Chứng khoán Thành phố Hồ Chí Minh | C99: HOSE | D99: HOSE | E99: Finance & investment | F99: Tài chính | G99: Vietnam Exchange | H99: Subsidiary | I99: =FALSE() -> FALSE | J99: 531 | P99: =SUM(K99:O99) -> 0
A100: 96 | B100: Tổng Công ty Cổ phần Bảo hiểm Ngân hàng Đầu tư và phát triển Việt Nam | C100: BIDV Insurance | D100: BIC | E100: Insurance | F100: Bảo hiểm | G100: BIDV | H100: Subsidiary | I100: =FALSE() -> FALSE | J100: 513 | K100: 216 | M100: 166 | P100: =SUM(K100:O100) -> 382
A101: 97 | B101: Công ty TNHH MTV Apatit Việt Nam | C101: Apatit Vietnam | D101: APATIT | E101: Chemicals & rubber | F101: Hóa chất | G101: Vinachem | H101: Subsidiary | I101: =FALSE() -> FALSE | J101: 496 | P101: =SUM(K101:O101) -> 0
...

Sheet STATE 100 groups
A1: Corporate groups inside STATE 100
A4: Corporate group | B4: Entries ranked | C4: Parent payment | D4: Subsidiaries ranked (memo) | E4: Share of STATE 100
A5: PetroVietnam | B5: 11 | C5: 90991 | D5: 54021 | E5: =C5/'STATE 100 firms'!$J$107 -> 0.21367666
A6: Viettel | B6: 4 | C6: 42290 | D6: 12696 | E6: =C6/'STATE 100 firms'!$J$107 -> 0.099310766
A7: Petrolimex | B7: 3 | C7: 30575 | D7: 1289 | E7: =C7/'STATE 100 firms'!$J$107 -> 0.07180011
A8: Vinacomin | B8: 4 | C8: 24031 | D8: 3418 | E8: =C8/'STATE 100 firms'!$J$107 -> 0.056432656
A9: EVN | B9: 8 | C9: 20891 | D9: 11305 | E9: =C9/'STATE 100 firms'!$J$107 -> 0.049058908
A10: BIDV | B10: 2 | C10: 11374 | D10: 513 | E10: =C10/'STATE 100 firms'!$J$107 -> 0.026709876
A11: MB | B11: 2 | C11: 10004 | D11: 834 | E11: =C11/'STATE 100 firms'!$J$107 -> 0.023492667
A12: HFIC | B12: 2 | C12: 6794 | D12: 6176 | E12: =C12/'STATE 100 firms'!$J$107 -> 0.015954536
A13: Vietnam Exchange | B13: 2 | C13: 3283 | D13: 531 | E13: =C13/'STATE 100 firms'!$J$107 -> 0.0077095589
A14: Vinachem | B14: 2 | C14: 2268 | D14: 496 | E14: =C14/'STATE 100 firms'!$J$107 -> 0.0053260066
A15: Bao Viet | B15: 2 | C15: 1817 | D15: 946 | E15: =C15/'STATE 100 firms'!$J$107 -> 0.0042669109
A16: Groups combined | B16: =SUM(B5:B15) -> 42 | C16: =SUM(C5:C15) -> 244318 | D16: =SUM(D5:D15) -> 92225
A17: Ungrouped, single-entity SOEs | B17: 58 | C17: 181517

Sheet Year on year
A1: Financial year 2024 against financial year 2025
A2: FY2024 from the VNTAX 200 list published in 2025; FY2025 from the list published in 2026. Same 200-firm cut-off, different constituents.
A4: Ownership | B4: FY2024 firms | C4: FY2024 (VND bn) | D4: FY2024 share | E4: FY2025 firms | F4: FY2025 (VND bn) | G4: FY2025 share | H4: Change
A5: State-owned (SOE) | B5: 75 | C5: 433090 | D5: =C5/$C$8 -> 0.54352164 | E5: 74 | F5: 445558 | G5: =F5/$F$8 -> 0.45039798 | H5: =F5/C5-1 -> 0.028788474
A6: Domestic private | B6: 101 | C6: 248990 | D6: =C6/$C$8 -> 0.31247882 | E6: 99 | F6: 390311 | G6: =F6/$F$8 -> 0.39455084 | H6: =F6/C6-1 -> 0.56757701
A7: Foreign-invested (FDI) | B7: 24 | C7: 114742 | D7: =C7/$C$8 -> 0.14399954 | E7: 27 | F7: 153385 | G7: =F7/$F$8 -> 0.15505118 | H7: =F7/C7-1 -> 0.33678165
A8: TOTAL | B8: =SUM(B5:B7) -> 200 | C8: =SUM(C5:C7) -> 796822 | D8: =C8/$C$8 -> 1 | E8: =SUM(E5:E7) -> 200 | F8: =SUM(F5:F7) -> 989254 | G8: =F8/$F$8 -> 1 | H8: =F8/C8-1 -> 0.24149936
A10: The state share falls from 54% to 45% between the two years. Almost all of the swing is one firm: Vingroup goes
A11: from VND 56,163 bn to VND 148,773 bn, of which VND 93,813 bn is land and land rent.
